perming/__init__.py
perming/_typing.py
perming/_utils.py
perming/_version.py
perming/common.py
perming/general.py
perming-1.9.3.dist-info/METADATA
perming-1.9.3.dist-info/WHEEL
perming-1.9.3.dist-info/top_level.txt
perming-1.9.3.dist-info/RECORD
