Metadata-Version: 2.1
Name: perming
Version: 1.9.3
Summary: The supervised learning framework based on perceptron for tabular data.
Home-page: https://github.com/linjing-lab/easy-pytorch/tree/main/released_box
Download-URL: https://github.com/linjing-lab/easy-pytorch/tags
Author: 林景
Author-email: linjing010729@163.com
License: MPL 2.0
Project-URL: Source, https://github.com/linjing-lab/easy-pytorch/tree/main/released_box/perming
Project-URL: Tracker, https://github.com/linjing-lab/easy-pytorch/issues
Platform: UNKNOWN
Classifier: Development Status :: 5 - Production/Stable
Classifier: Intended Audience :: Developers
Classifier: Intended Audience :: Education
Classifier: Intended Audience :: Science/Research
Classifier: Operating System :: Microsoft :: Windows
Classifier: Programming Language :: Python :: 3.7
Classifier: Programming Language :: Python :: 3.8
Classifier: Programming Language :: Python :: 3.9
Classifier: Programming Language :: Python :: 3.10
Classifier: Programming Language :: Python :: 3.11
Classifier: License :: OSI Approved :: Mozilla Public License 2.0 (MPL 2.0)
Classifier: Topic :: Software Development
Classifier: Topic :: Software Development :: Libraries
Classifier: Topic :: Software Development :: Libraries :: Python Modules
Classifier: Topic :: Scientific/Engineering
Classifier: Topic :: Scientific/Engineering :: Artificial Intelligence
Requires-Dist: numpy (>=1.21.0)
Requires-Dist: joblib (>=1.3.2)
